djarango/db/backends/arangodb/__init__.py
djarango/db/backends/arangodb/base.py
djarango/db/backends/arangodb/client.py
djarango/db/backends/arangodb/compiler.py
djarango/db/backends/arangodb/creation.py
djarango/db/backends/arangodb/features.py
djarango/db/backends/arangodb/introspection.py
djarango/db/backends/arangodb/operations.py
djarango/db/backends/arangodb/schema.py
djarango/db/backends/arangodb/fields/__init__.py
djarango/db/backends/arangodb/fields/edge_descriptors.py
djarango/db/backends/arangodb/fields/edges.py
djarango/scripts/__init__.py
djarango/scripts/check_updates.sh
djarango/scripts/djarango.py
djarango/scripts/finddist.py
djarango/scripts/install.sh
djarango-0.0.6.dist-info/LICENSE
djarango-0.0.6.dist-info/METADATA
djarango-0.0.6.dist-info/WHEEL
djarango-0.0.6.dist-info/entry_points.txt
djarango-0.0.6.dist-info/top_level.txt
djarango-0.0.6.dist-info/RECORD
