Metadata-Version: 2.1
Name: djarango
Version: 0.0.6
Summary: ArangoDB Graph Database Backend for Django
Home-page: https://github.com/timothygraefe/djarango
Author: Timothy Graefe
Author-email: tgraefe@javamata.net
License: Apache
Project-URL: Bug Reports, https://github.com/timothygraefe/djarango/issues
Project-URL: Source, https://github.com/timothygraefe/imgutils/
Keywords: django,arangodb,database,nosql
Platform: UNKNOWN
Classifier: Development Status :: 2 - Pre-Alpha
Classifier: Framework :: Django :: 2.2
Classifier: Programming Language :: Python :: 3
Classifier: License :: OSI Approved :: Apache Software License
Classifier: Operating System :: POSIX :: Linux
Classifier: Intended Audience :: Developers
Classifier: Topic :: Database :: Front-Ends
Classifier: Programming Language :: Python :: 3
Classifier: Programming Language :: Python :: 3.6
Classifier: Programming Language :: Python :: 3.7
Classifier: Programming Language :: Python :: 3.8
Classifier: Programming Language :: Python :: 3.9
Requires-Python: >=3.6, <4
License-File: LICENSE
Requires-Dist: Django
